{
  "slug": "hard-filing-wall",
  "potassiumEnemyKind": "hardWall",
  "assetClass": "enemy",
  "sourceManifest": "manifest.json",
  "phaserTextureKey": "potassium_enemy_hard_wall",
  "spritesheet": "hard-filing-wall-spritesheet.png",
  "frameWidth": 80,
  "frameHeight": 62,
  "frameCount": 5,
  "origin": {
    "x": 0.5,
    "y": 0.5
  },
  "runtimeScale": 0.78,
  "states": [
    {
      "index": 0,
      "state": "intact",
      "file": "frames/00-intact.png"
    },
    {
      "index": 1,
      "state": "tilt-left",
      "file": "frames/01-tilt-left.png"
    },
    {
      "index": 2,
      "state": "tilt-right",
      "file": "frames/02-tilt-right.png"
    },
    {
      "index": 3,
      "state": "deflect",
      "file": "frames/03-deflect.png"
    },
    {
      "index": 4,
      "state": "invulnerable",
      "file": "frames/04-invulnerable.png"
    }
  ],
  "animations": {
    "idle": {
      "key": "potassium_enemy_hard_wall_idle",
      "frames": [
        0,
        1,
        2,
        1
      ],
      "frameRate": 8,
      "repeat": -1
    },
    "deflect": {
      "key": "potassium_enemy_hard_wall_deflect",
      "frames": [
        3
      ],
      "frameRate": 14,
      "repeat": 0
    },
    "invulnerable": {
      "key": "potassium_enemy_hard_wall_invulnerable",
      "frames": [
        4
      ],
      "frameRate": 8,
      "repeat": 0
    }
  },
  "hitboxCompatibility": {
    "kind": "bodyProfile",
    "currentTexture": "potassium_enemy_hard_wall",
    "runtimeScale": 0.78,
    "body": {
      "width": 68,
      "height": 52
    },
    "indestructible": true
  },
  "bodyPhysics": {
    "type": "arcade-rectangle",
    "width": 68,
    "height": 52
  },
  "debugContact": "hard-filing-wall-debug-contact.png",
  "preload": {
    "method": "spritesheet",
    "key": "potassium_enemy_hard_wall",
    "url": "/assets/potassium-slip/enemies/hard-filing-wall/hard-filing-wall-spritesheet.png",
    "config": {
      "frameWidth": 80,
      "frameHeight": 62
    }
  }
}
